{
    "code": 200,
    "msg": "数据爬取成功!",
    "data": [
        {
            "热门城市": [
                "北京",
                "上海",
                "三亚",
                "香港",
                "杭州",
                "广州",
                "成都",
                "深圳",
                "苏州",
                "桂林",
                "西安",
                "厦门"
            ],
            "A": [
                "阿坝藏族羌族自治州",
                "阿克苏地区",
                "阿拉尔",
                "阿拉善盟",
                "阿勒泰",
                "阿里",
                "安康",
                "安庆",
                "安顺",
                "安阳",
                "鞍山",
                "澳门"
            ],
            "B": [
                "巴彦淖尔",
                "巴音郭楞",
                "巴中",
                "白城",
                "白沙",
                "白山",
                "白银",
                "百色",
                "蚌埠",
                "包头",
                "宝鸡",
                "保定",
                "保山",
                "保亭",
                "北海",
                "北京",
                "本溪",
                "毕节",
                "滨州",
                "亳州",
                "博尔塔拉"
            ],
            "C": [
                "沧州",
                "昌都",
                "昌吉",
                "常德",
                "常州",
                "巢湖",
                "朝阳",
                "潮州",
                "郴州",
                "成都",
                "承德",
                "澄迈",
                "池州",
                "赤峰",
                "崇左",
                "滁州",
                "楚雄",
                "长春",
                "长葛市",
                "长沙",
                "长治",
                "重庆"
            ],
            "D": [
                "达州",
                "大理",
                "大连",
                "大庆",
                "大同",
                "大兴安岭",
                "丹东",
                "儋州",
                "淡水",
                "德宏",
                "德阳",
                "德州市",
                "迪庆",
                "定安",
                "定西",
                "东方",
                "东莞",
                "东营",
                "敦煌市"
            ],
            "E": [
                "鄂尔多斯",
                "鄂州",
                "恩施"
            ],
            "F": [
                "防城港",
                "佛山",
                "福州",
                "抚顺",
                "抚州",
                "阜新",
                "阜阳"
            ],
            "G": [
                "甘南",
                "甘孜州",
                "赣州",
                "高雄",
                "固原",
                "广安",
                "广元",
                "广州",
                "贵港",
                "贵阳",
                "桂林",
                "果洛藏族自治州"
            ],
            "H": [
                "哈尔滨",
                "哈密",
                "海北藏族自治州",
                "海东地区",
                "海口",
                "海南藏族自治州",
                "海西蒙古族藏族自治州",
                "邯郸",
                "汉中",
                "杭州",
                "合肥",
                "和田",
                "河池",
                "河源",
                "菏泽",
                "贺州",
                "鹤壁",
                "鹤岗",
                "黑河",
                "衡水",
                "衡阳",
                "红河",
                "呼和浩特",
                "呼伦贝尔",
                "葫芦岛",
                "湖州",
                "花莲",
                "怀化",
                "淮安",
                "淮北",
                "淮南",
                "黄冈",
                "黄南藏族自治州",
                "黄山市",
                "黄石",
                "惠州"
            ],
            "J": [
                "鸡西",
                "基隆",
                "吉安",
                "吉林",
                "济南",
                "济宁",
                "济源",
                "佳木斯",
                "嘉兴",
                "嘉义",
                "嘉峪关",
                "江门",
                "焦作",
                "揭阳",
                "金昌",
                "金华",
                "锦州",
                "晋城",
                "晋中",
                "荆门",
                "荆州",
                "景德镇",
                "九江",
                "酒泉"
            ],
            "K": [
                "喀什",
                "开封",
                "克拉玛依",
                "克孜勒苏",
                "克孜勒苏柯尔克孜",
                "昆明"
            ],
            "L": [
                "拉萨",
                "来宾",
                "莱芜",
                "莱州市",
                "兰州",
                "廊坊",
                "乐东",
                "乐山",
                "丽江",
                "丽水",
                "连云港",
                "凉山州",
                "辽阳",
                "辽源",
                "聊城",
                "林芝",
                "临沧",
                "临汾",
                "临高",
                "临夏",
                "临沂",
                "陵水",
                "柳州",
                "六安",
                "六盘水",
                "龙岩",
                "陇南",
                "娄底",
                "泸州",
                "洛阳",
                "漯河",
                "吕梁"
            ],
            "M": [
                "马鞍山",
                "茂名",
                "眉山",
                "梅州",
                "绵阳",
                "苗栗",
                "牡丹江"
            ],
            "N": [
                "那曲",
                "南昌",
                "南充",
                "南京",
                "南宁",
                "南平",
                "南通",
                "南投",
                "南阳",
                "内江",
                "宁波",
                "宁德",
                "怒江"
            ],
            "P": [
                "攀枝花",
                "盘锦",
                "平顶山",
                "平湖",
                "平凉",
                "屏东",
                "萍乡",
                "莆田",
                "濮阳",
                "普宁"
            ],
            "Q": [
                "七台河",
                "齐齐哈尔",
                "潜江",
                "黔东南",
                "黔南",
                "黔西南",
                "钦州",
                "秦皇岛",
                "青岛",
                "清远",
                "庆阳",
                "琼海",
                "琼中",
                "衢州",
                "曲靖",
                "泉州"
            ],
            "R": [
                "日喀则",
                "日照",
                "瑞金市"
            ],
            "S": [
                "普洱",
                "三门峡",
                "三明",
                "三沙",
                "三亚",
                "山南",
                "汕头",
                "汕尾",
                "商洛",
                "商丘",
                "上海",
                "上饶",
                "韶关",
                "邵阳",
                "绍兴",
                "深圳",
                "神农架",
                "沈阳",
                "十堰",
                "石河子",
                "石家庄",
                "石嘴山",
                "双鸭山",
                "朔州",
                "四平",
                "松原",
                "苏州",
                "绥化",
                "随州",
                "遂宁",
                "宿迁",
                "宿州"
            ],
            "T": [
                "塔城地区",
                "台北",
                "台东",
                "台南",
                "台山市",
                "台中",
                "台州",
                "太原",
                "泰安",
                "泰州",
                "唐山",
                "桃园",
                "天津",
                "天门",
                "天水",
                "铁岭",
                "通化",
                "通辽",
                "铜川",
                "铜陵",
                "铜仁",
                "图木舒克",
                "吐鲁番",
                "屯昌"
            ],
            "W": [
                "万宁",
                "威海",
                "潍坊",
                "渭南",
                "温州",
                "文昌",
                "文山",
                "乌海",
                "乌兰察布",
                "乌鲁木齐",
                "无锡",
                "芜湖",
                "吴忠",
                "梧州",
                "五家渠市",
                "五指山",
                "武汉",
                "武威"
            ],
            "X": [
                "厦门",
                "西安",
                "西南中沙群岛办事处",
                "西宁",
                "西双版纳",
                "锡林郭勒盟",
                "仙桃",
                "咸宁",
                "咸阳",
                "香港",
                "湘潭",
                "湘西",
                "襄樊",
                "襄阳",
                "孝感",
                "忻州",
                "新北",
                "新乡",
                "新余",
                "新竹",
                "信阳",
                "邢台",
                "兴安盟",
                "徐州",
                "许昌",
                "宣城"
            ],
            "Y": [
                "雅安",
                "烟台",
                "延安",
                "延边",
                "盐城",
                "扬州",
                "阳江",
                "阳泉",
                "伊春",
                "伊犁",
                "伊犁哈萨克自治州",
                "宜宾",
                "宜昌",
                "宜春",
                "宜兰",
                "益阳",
                "银川",
                "鹰潭",
                "营口",
                "永州",
                "榆林",
                "玉林",
                "玉树藏族自治州",
                "玉溪",
                "岳阳",
                "云浮",
                "云林",
                "运城"
            ],
            "Z": [
                "枣庄",
                "湛江",
                "张家界",
                "张家口",
                "张掖",
                "彰化",
                "漳州",
                "昭通",
                "肇庆",
                "镇江",
                "郑州",
                "中山",
                "中卫",
                "舟山",
                "周口",
                "珠海",
                "株洲",
                "驻马店",
                "资阳",
                "淄博",
                "自贡",
                "遵义"
            ]
        },
        {
            "热门城市": [
                "香港",
                "澳门",
                "台湾",
                "曼谷",
                "新加坡",
                "首尔",
                "东京",
                "济州岛",
                "芭堤雅",
                "巴厘岛",
                "清迈",
                "悉尼",
                "大阪",
                "洛杉矶",
                "旧金山",
                "罗马",
                "巴黎",
                "伦敦",
                "米兰",
                "纽约"
            ],
            "A": [
                "阿富汗",
                "阿尔巴尼亚",
                "阿尔及利亚",
                "美国",
                "安哥拉",
                "安提瓜和巴布达",
                "阿联酋",
                "阿根廷",
                "亚美尼亚",
                "阿鲁巴",
                "澳大利亚",
                "奥地利",
                "阿塞拜疆"
            ],
            "B": [
                "巴林",
                "瓦努阿图",
                "白俄罗斯",
                "孟加拉国",
                "孟加拉",
                "巴巴多斯",
                "比利时",
                "伯利兹",
                "贝宁",
                "不丹",
                "委内瑞拉",
                "玻利维亚",
                "波黑",
                "博茨瓦纳",
                "巴西",
                "文莱",
                "保加利亚",
                "布基纳法索",
                "布隆迪"
            ],
            "C": [
                "柬埔寨",
                "喀麦隆",
                "加拿大",
                "佛得角",
                "加罗林群岛",
                "开曼群岛",
                "哥伦比亚",
                "厄立特里亚",
                "刚果（金）",
                "刚果",
                "哥斯达黎加",
                "克罗地亚",
                "古巴",
                "塞浦路斯",
                "捷克"
            ],
            "D": [
                "丹麦",
                "多米尼加"
            ],
            "E": [
                "东帝汶民主共和国",
                "厄瓜多尔",
                "埃及",
                "赤道几内亚",
                "爱沙尼亚"
            ],
            "F": [
                "斐济",
                "芬兰",
                "法国",
                "法属波利尼西亚"
            ],
            "G": [
                "加蓬",
                "冈比亚",
                "加纳",
                "格鲁吉亚",
                "德国",
                "格陵兰岛",
                "格林纳达",
                "关岛",
                "危地马拉",
                "几内亚",
                "圭亚那"
            ],
            "H": [
                "海地",
                "希腊",
                "幸福岛",
                "洪都拉斯",
                "香港",
                "匈牙利"
            ],
            "I": [
                "冰岛",
                "印度",
                "印度尼西亚",
                "印度尼西亚",
                "伊朗",
                "伊拉克",
                "爱尔兰",
                "以色列",
                "意大利"
            ],
            "J": [
                "牙买加",
                "日本",
                "约旦"
            ],
            "K": [
                "哈萨克斯坦",
                "肯尼亚",
                "朝鲜",
                "韩国",
                "科威特",
                "吉尔吉斯斯坦"
            ],
            "L": [
                "老挝",
                "拉脱维亚",
                "黎巴嫩",
                "莱索托",
                "利比里亚",
                "利比亚",
                "立陶宛",
                "卢森堡"
            ],
            "M": [
                "澳门",
                "马其顿",
                "马达加斯加",
                "塞舌尔",
                "马拉维",
                "马来西亚",
                "马尔代夫",
                "马里",
                "马耳他",
                "马里亚纳群岛",
                "毛里塔尼亚",
                "毛里求斯",
                "墨西哥",
                "摩尔多瓦",
                "摩洛哥",
                "摩纳哥",
                "蒙古",
                "黑山共和国",
                "莫桑比克"
            ],
            "N": [
                "纳米比亚",
                "尼泊尔",
                "荷兰",
                "新喀里多尼亚",
                "新西兰",
                "尼日尔",
                "尼日利亚",
                "北马里亚那群岛",
                "挪威"
            ],
            "O": [
                "阿曼"
            ],
            "P": [
                "巴基斯坦",
                "帕劳共和国",
                "巴拿马",
                "巴布亚新几内亚",
                "巴拉圭",
                "菲律宾",
                "波兰",
                "葡萄牙",
                "列支敦士登",
                "波多黎各"
            ],
            "R": [
                "智利",
                "罗马尼亚",
                "俄罗斯",
                "卢旺达"
            ],
            "S": [
                "圣卢西亚",
                "圣文森特和格林纳丁斯",
                "所罗门群岛",
                "沙特阿拉伯",
                "沙特",
                "塞内加尔",
                "塞尔维亚共和国",
                "塞尔维亚",
                "塞拉利昂",
                "新加坡",
                "斯洛伐克",
                "斯洛文尼亚",
                "南非",
                "西班牙",
                "斯里兰卡",
                "卡塔尔",
                "苏丹",
                "瑞典",
                "瑞士"
            ],
            "T": [
                "秘鲁",
                "塔吉克斯坦",
                "坦桑尼亚",
                "泰国",
                "巴尔干半岛",
                "英属维尔京群岛",
                "中非",
                "多米尼克",
                "巴哈马",
                "科摩罗",
                "埃塞俄比亚",
                "圣基茨和尼维斯联邦",
                "科特迪瓦",
                "安道尔",
                "几内亚比绍共和国",
                "叙利亚",
                "多哥",
                "汤加",
                "突尼斯",
                "土耳其",
                "土库曼斯坦",
                "特克斯和凯科斯群岛"
            ],
            "U": [
                "乌干达",
                "英国",
                "乌克兰",
                "缅甸",
                "乌拉圭",
                "乌兹别克斯坦"
            ],
            "V": [
                "梵蒂冈",
                "越南"
            ],
            "Y": [
                "也门共和国"
            ],
            "Z": [
                "赞比亚",
                "津巴布韦"
            ]
        }
    ]
}